otlk/__init__.py
otlk/const.py
otlk/ingest.py
otlk/main.py
otlk/model.py
otlk/util.py
otlk-0.3.1.dist-info/entry_points.txt
otlk-0.3.1.dist-info/LICENSE
otlk-0.3.1.dist-info/WHEEL
otlk-0.3.1.dist-info/METADATA
otlk-0.3.1.dist-info/RECORD
