Metadata-Version: 2.1
Name: otlk
Version: 0.3.1
Summary: outlookの情報を取得するためのCLIツール
Author: Hiroaki Hasegawa
Author-email: hasepappa@gmail.com
Requires-Python: >=3.8,<4.0
Classifier: Programming Language :: Python :: 3
Classifier: Programming Language :: Python :: 3.8
Requires-Dist: click (>=7.0,<8.0)
Requires-Dist: numpy (>=1.18.1,<2.0.0)
Requires-Dist: pandas (>=1.0.0,<2.0.0)
Requires-Dist: pyyaml (>=5.3,<6.0)
Requires-Dist: requests (>=2.23.0,<3.0.0)
Requires-Dist: tabulate (>=0.8.6,<0.9.0)
Requires-Dist: tqdm (>=4.42.0,<5.0.0)
